<Cloud Material="Materials/clouds/cloud_a" TextureNumCols="4" TextureNumRows="4" >
 <Sprite Angle="-1.4675839" Pos="-63.168098,48.589664,55.030861" Radius="23.821512" texID="8" />
 <Sprite Angle="-1.1416032" Pos="19.744589,134.82582,53.676968" Radius="28.002029" texID="8" />
 <Sprite Angle="2.1199286" Pos="-126.58862,94.339966,53.497032" Radius="24.114399" texID="11" />
 <Sprite Angle="1.9099587" Pos="-5.8177152,-98.421043,52.388203" Radius="28.251335" texID="9" />
 <Sprite Angle="1.0754484" Pos="-33.449173,133.77293,57.034676" Radius="25.489105" texID="8" />
 <Sprite Angle="-2.7820528" Pos="-162.515,-132.73605,59.20097" Radius="26.998398" texID="11" />
 <Sprite Angle="-0.57765681" Pos="-58.196632,54.906998,54.344009" Radius="25.211386" texID="10" />
 <Sprite Angle="0.20354612" Pos="-98.023285,-60.700169,49.724728" Radius="24.029587" texID="9" />
 <Sprite Angle="0.41006443" Pos="-186.20042,-106.65189,49.259445" Radius="25.518372" texID="11" />
 <Sprite Angle="-2.8359354" Pos="43.768761,34.66407,51.197796" Radius="22.235954" texID="11" />
 <Sprite Angle="-2.7498381" Pos="-157.10406,-75.02861,54.678371" Radius="25.102009" texID="8" />
 <Sprite Angle="-1.1486981" Pos="-137.84079,-75.532166,53.708858" Radius="28.424589" texID="8" />
 <Sprite Angle="-0.24937516" Pos="-126.44212,-86.912514,58.495995" Radius="25.258598" texID="9" />
 <Sprite Angle="-2.1066976" Pos="97.347054,103.26662,50.69659" Radius="24.5047" texID="9" />
 <Sprite Angle="0.040364064" Pos="-154.70532,-61.753056,57.453632" Radius="25.993698" texID="9" />
 <Sprite Angle="-1.2635584" Pos="-147.9119,-113.64673,54.372883" Radius="26.078081" texID="11" />
 <Sprite Angle="-2.6370871" Pos="-183.3622,-11.214405,51.303879" Radius="25.855267" texID="9" />
 <Sprite Angle="2.8767788" Pos="53.226444,-111.87971,58.231457" Radius="26.96443" texID="9" />
 <Sprite Angle="-2.3028612" Pos="92.824211,140.2276,49.200359" Radius="21.782846" texID="10" />
 <Sprite Angle="-1.3285627" Pos="18.1973,-15.490048,56.296463" Radius="23.692694" texID="10" />
 <Sprite Angle="1.3653793" Pos="97.859764,1.6674573,57.720516" Radius="22.752724" texID="10" />
 <Sprite Angle="1.8691152" Pos="-57.281078,-87.104782,58.26738" Radius="23.493591" texID="9" />
 <Sprite Angle="1.2064159" Pos="-118.53172,-142.66983,58.421131" Radius="24.495514" texID="10" />
 <Sprite Angle="1.3634619" Pos="74.806084,-87.736519,56.217907" Radius="26.817026" texID="8" />
 <Sprite Angle="-1.8110141" Pos="-98.252174,81.293297,54.341995" Radius="22.074877" texID="11" />
 <Sprite Angle="0.82827836" Pos="91.029724,-142.92619,58.001503" Radius="27.912947" texID="8" />
 <Sprite Angle="0.49271008" Pos="-26.115576,53.606907,50.356857" Radius="21.603397" texID="9" />
 <Sprite Angle="-1.8288471" Pos="-59.505878,-12.285605,55.023811" Radius="24.504272" texID="9" />
 <Sprite Angle="0.36576942" Pos="-74.191383,55.941574,57.780609" Radius="22.877697" texID="9" />
 <Sprite Angle="-0.78820193" Pos="-27.708641,-109.23376,50.537468" Radius="24.081072" texID="10" />
 <Sprite Angle="1.6037287" Pos="-148.69928,-125.20103,54.136211" Radius="25.216299" texID="9" />
 <Sprite Angle="1.7741973" Pos="111.90438,32.283627,49.111732" Radius="23.849926" texID="10" />
 <Sprite Angle="-2.2911642" Pos="101.14661,-9.5023174,54.49575" Radius="28.278465" texID="8" />
 <Sprite Angle="2.6165695" Pos="102.23612,96.976761,56.439137" Radius="21.868938" texID="10" />
 <Sprite Angle="-1.2946224" Pos="103.00519,-19.976269,49.290329" Radius="24.147724" texID="8" />
 <Sprite Angle="1.0846525" Pos="-24.95282,-63.282036,56.129284" Radius="22.39938" texID="11" />
 <Sprite Angle="0.38935506" Pos="50.672047,11.857588,53.003548" Radius="22.459837" texID="11" />
 <Sprite Angle="1.6476402" Pos="68.149994,81.311615,56.652981" Radius="23.006088" texID="8" />
 <Sprite Angle="0.27085152" Pos="53.25391,60.91304,51.650997" Radius="27.856762" texID="9" />
 <Sprite Angle="1.7701706" Pos="54.178623,114.61036,54.085518" Radius="23.43527" texID="9" />
 <Sprite Angle="-2.0294211" Pos="-115.11671,21.782207,49.455494" Radius="25.548708" texID="10" />
 <Sprite Angle="-1.3055524" Pos="-103.45253,-30.679111,58.811218" Radius="22.804636" texID="10" />
 <Sprite Angle="2.6459079" Pos="-74.228004,148.23871,57.61813" Radius="27.264153" texID="8" />
 <Sprite Angle="1.5864708" Pos="98.106964,43.389313,53.841125" Radius="24.135548" texID="8" />
 <Sprite Angle="-2.2280774" Pos="-165.01447,-102.66922,49.598167" Radius="23.370113" texID="9" />
 <Sprite Angle="0.93681073" Pos="-41.762417,91.227074,54.905979" Radius="26.755928" texID="9" />
 <Sprite Angle="-1.0413163" Pos="45.718891,6.0621228,55.804993" Radius="26.443815" texID="10" />
 <Sprite Angle="1.0543555" Pos="-96.009064,-7.1310291,51.971256" Radius="25.610233" texID="10" />
 <Sprite Angle="-1.9590476" Pos="-76.342941,-121.255,59.104622" Radius="24.075945" texID="9" />
 <Sprite Angle="-1.5738152" Pos="10.836235,-45.822395,57.342178" Radius="26.003311" texID="8" />
 <Sprite Angle="-1.7600076" Pos="79.063416,-86.628693,51.056801" Radius="26.189383" texID="10" />
 <Sprite Angle="-0.78628439" Pos="-121.28754,-58.768349,51.00309" Radius="22.811045" texID="9" />
 <Sprite Angle="2.753865" Pos="-26.820553,-55.188526,53.279495" Radius="24.64954" texID="10" />
 <Sprite Angle="2.6453326" Pos="78.935234,102.03978,59.360764" Radius="22.690344" texID="11" />
 <Sprite Angle="-1.7966325" Pos="109.59718,133.24191,56.848358" Radius="22.455351" texID="9" />
 <Sprite Angle="-0.41236547" Pos="-162.32274,-121.40148,59.030434" Radius="23.316492" texID="8" />
 <Sprite Angle="2.643415" Pos="-48.79388,-24.233603,58.144512" Radius="27.283594" texID="11" />
 <Sprite Angle="1.0269347" Pos="-128.40141,-37.353508,51.841003" Radius="28.183401" texID="9" />
 <Sprite Angle="-0.34774461" Pos="-46.614857,-30.569244,56.048714" Radius="26.673895" texID="11" />
 <Sprite Angle="1.2232901" Pos="-58.828365,-2.0313859,57.699368" Radius="24.992203" texID="8" />
 <Sprite Angle="-2.147541" Pos="53.958889,103.70609,56.892338" Radius="21.634159" texID="8" />
 <Sprite Angle="-2.915513" Pos="37.506359,82.575081,52.476826" Radius="27.16802" texID="8" />
 <Sprite Angle="-0.3182146" Pos="10.708057,10.566655,51.069893" Radius="23.945845" texID="8" />
 <Sprite Angle="-0.055704337" Pos="-131.86221,-126.20815,59.575615" Radius="22.525208" texID="9" />
 <Sprite Angle="-0.61754149" Pos="-73.111031,50.429932,51.720486" Radius="23.951185" texID="10" />
 <Sprite Angle="-2.0811944" Pos="-142.51012,49.40451,59.326187" Radius="26.623478" texID="10" />
 <Sprite Angle="1.3740082" Pos="55.506176,61.773663,49.383991" Radius="23.107136" texID="11" />
 <Sprite Angle="-0.18686359" Pos="-172.43962,-72.034744,56.87891" Radius="21.835825" texID="9" />
 <Sprite Angle="3.0518496" Pos="22.912409,-147.09196,50.037941" Radius="26.080217" texID="8" />
 <Sprite Angle="-0.63153946" Pos="74.622971,-98.54007,49.736813" Radius="21.669409" texID="9" />
 <Sprite Angle="2.2857952" Pos="-137.64851,-36.209064,50.419636" Radius="23.670477" texID="9" />
 <Sprite Angle="-2.8971047" Pos="107.28083,83.353302,59.598442" Radius="27.361782" texID="11" />
 <Sprite Angle="-1.2014303" Pos="-1.8808274,-123.9101,52.046455" Radius="22.342127" texID="10" />
 <Sprite Angle="0.22118743" Pos="61.805199,-74.845497,57.649349" Radius="25.288721" texID="11" />
 <Sprite Angle="-0.56826091" Pos="-129.11554,-0.36507535,55.829498" Radius="25.64185" texID="10" />
 <Sprite Angle="-0.38609526" Pos="60.257908,104.7956,57.980686" Radius="23.21694" texID="10" />
 <Sprite Angle="2.759234" Pos="-155.06238,113.34689,50.698605" Radius="23.287867" texID="8" />
 <Sprite Angle="1.5022912" Pos="-173.1629,39.653847,54.26915" Radius="21.924696" texID="9" />
 <Sprite Angle="-1.8062202" Pos="87.788658,-11.251028,59.135845" Radius="26.211172" texID="10" />
 <Sprite Angle="-0.34889513" Pos="-171.50575,127.62955,52.392231" Radius="25.230186" texID="11" />
 <Sprite Angle="-0.97439438" Pos="-137.09003,-25.671024,55.029182" Radius="28.326319" texID="9" />
 <Sprite Angle="-2.8769705" Pos="-45.003483,-30.807289,50.121197" Radius="26.95439" texID="10" />
 <Sprite Angle="0.024640296" Pos="-73.788536,68.622017,58.750122" Radius="24.319483" texID="9" />
 <Sprite Angle="1.1937602" Pos="4.354104,-126.30886,51.559349" Radius="21.851208" texID="10" />
 <Sprite Angle="-1.5718976" Pos="66.804131,60.391174,48.861969" Radius="27.228477" texID="9" />
 <Sprite Angle="-0.12742007" Pos="89.125366,-97.139267,55.473316" Radius="28.035784" texID="9" />
 <Sprite Angle="0.36116734" Pos="-117.26826,-136.08699,50.366932" Radius="26.100086" texID="9" />
 <Sprite Angle="0.72664911" Pos="-170.72754,-145.13268,50.179272" Radius="27.93965" texID="9" />
 <Sprite Angle="0.71303463" Pos="-67.636009,-72.5383,49.893253" Radius="23.506195" texID="10" />
 <Sprite Angle="2.2219412" Pos="-152.83759,141.83897,53.137157" Radius="25.330805" texID="9" />
 <Sprite Angle="3.0322907" Pos="-48.143837,-56.82737,53.735378" Radius="23.19515" texID="9" />
 <Sprite Angle="-2.8685334" Pos="-69.732628,64.080864,51.91016" Radius="27.421812" texID="11" />
 <Sprite Angle="-1.6528175" Pos="-20.448288,-63.556702,49.14732" Radius="23.667059" texID="9" />
 <Sprite Angle="-2.397012" Pos="77.333015,34.15136,49.645504" Radius="23.602757" texID="9" />
 <Sprite Angle="0.89309096" Pos="-122.12986,-137.11241,52.800781" Radius="27.946913" texID="11" />
 <Sprite Angle="-0.77765548" Pos="-6.4128261,53.799175,49.733456" Radius="21.828348" texID="11" />
 <Sprite Angle="3.0992126" Pos="93.181274,-8.9163618,50.80838" Radius="27.341913" texID="10" />
 <Sprite Angle="-0.66797262" Pos="-49.434769,96.976761,50.800995" Radius="25.189383" texID="8" />
 <Sprite Angle="-1.9132185" Pos="44.418804,-0.84116411,58.22575" Radius="25.463255" texID="9" />
 <Sprite Angle="-0.49328536" Pos="76.170258,102.07641,51.692959" Radius="23.703161" texID="10" />
 <Sprite Angle="1.1473558" Pos="-18.873533,-36.621063,58.429188" Radius="25.289576" texID="8" />
 <Sprite Angle="0.62770438" Pos="90.718437,126.37524,49.603539" Radius="23.849712" texID="10" />
 <Sprite Angle="-1.4666251" Pos="1.3419272,-33.141956,50.285019" Radius="24.560884" texID="10" />
 <Sprite Angle="2.1431308" Pos="-145.58638,-133.97206,53.00724" Radius="22.888805" texID="10" />
 <Sprite Angle="0.083508559" Pos="-29.89682,6.4832783,51.510674" Radius="26.275902" texID="10" />
 <Sprite Angle="1.3885815" Pos="42.074982,-105.45251,59.550774" Radius="27.487183" texID="10" />
 <Sprite Angle="-1.6541598" Pos="29.21143,-73.746834,55.13493" Radius="25.580751" texID="10" />
 <Sprite Angle="-1.7277931" Pos="10.515791,-77.070297,53.558128" Radius="23.686712" texID="8" />
 <Sprite Angle="-1.8428451" Pos="38.778984,-144.94041,51.46233" Radius="21.826639" texID="9" />
 <Sprite Angle="1.1975952" Pos="-25.557087,34.66407,50.311874" Radius="25.747597" texID="11" />
 <Sprite Angle="1.022141" Pos="41.241825,-22.851112,57.456318" Radius="24.078936" texID="9" />
 <Sprite Angle="1.8286552" Pos="56.293556,-101.36913,53.892899" Radius="26.892651" texID="12" />
 <Sprite Angle="1.4338353" Pos="88.511948,113.22787,56.069263" Radius="21.857616" texID="12" />
 <Sprite Angle="2.5381424" Pos="25.750631,113.05392,48.920456" Radius="28.491241" texID="14" />
 <Sprite Angle="-1.1339331" Pos="22.756765,40.53278,56.61478" Radius="22.394039" texID="12" />
 <Sprite Angle="1.3101544" Pos="94.527145,83.637123,56.909531" Radius="26.706152" texID="14" />
 <Sprite Angle="0.89328271" Pos="-48.427658,129.86351,56.647346" Radius="28.178488" texID="13" />
 <Sprite Angle="-0.91399211" Pos="-17.930511,-111.00078,48.644173" Radius="28.141102" texID="15" />
 <Sprite Angle="2.3172426" Pos="-91.870758,-72.300255,51.500336" Radius="28.088121" texID="14" />
 <Sprite Angle="-2.8403456" Pos="-82.239113,-63.410213,51.297237" Radius="22.515808" texID="13" />
 <Sprite Angle="-2.5580847" Pos="36.838005,-38.406399,47.955643" Radius="22.870007" texID="12" />
 <Sprite Angle="-0.65474164" Pos="-104.73431,-137.97304,53.61594" Radius="25.904613" texID="12" />
 <Sprite Angle="-2.1912608" Pos="95.277901,-103.08122,51.127708" Radius="25.263084" texID="12" />
 <Sprite Angle="-0.91111577" Pos="-55.321789,75.314728,48.975845" Radius="24.560884" texID="13" />
 <Sprite Angle="-0.56749386" Pos="-87.045776,123.13418,48.099659" Radius="27.540377" texID="14" />
 <Sprite Angle="-2.3377602" Pos="-161.96567,-93.358025,56.456665" Radius="23.872356" texID="15" />
 <Sprite Angle="-2.4819589" Pos="-102.46373,-102.43118,51.226402" Radius="23.752296" texID="14" />
 <Sprite Angle="2.1975887" Pos="93.895409,-44.687107,53.593784" Radius="25.464109" texID="15" />
 <Sprite Angle="-1.0200317" Pos="-70.895386,25.142294,49.500885" Radius="23.45236" texID="14" />
 <Sprite Angle="-0.56826091" Pos="-3.5105159,-105.40673,56.96492" Radius="24.990707" texID="13" />
 <Sprite Angle="-1.2039231" Pos="-66.793694,-98.265404,51.899826" Radius="25.186605" texID="14" />
 <Sprite Angle="-1.5648028" Pos="-104.73431,-64.206749,53.267147" Radius="21.643345" texID="14" />
 <Sprite Angle="2.4689195" Pos="-126.82666,-100.29794,49.105427" Radius="26.527771" texID="13" />
 <Sprite Angle="-0.035570238" Pos="-99.790306,-95.34478,50.041035" Radius="26.90782" texID="14" />
 <Sprite Angle="-2.2115867" Pos="52.448223,123.43631,55.519718" Radius="24.936018" texID="15" />
 <Sprite Angle="-1.7260673" Pos="-161.23323,-66.843544,58.694801" Radius="21.596775" texID="14" />
 <Sprite Angle="2.1567452" Pos="67.445015,-86.857582,57.965317" Radius="23.226555" texID="13" />
 <Sprite Angle="-1.3013338" Pos="89.894432,19.887007,47.990555" Radius="23.698462" texID="12" />
 <Sprite Angle="0.7013377" Pos="1.7173048,-74.854652,54.994003" Radius="21.926405" texID="14" />
 <Sprite Angle="-0.24208854" Pos="60.816399,62.066639,54.644203" Radius="27.062273" texID="13" />
 <Sprite Angle="1.9692105" Pos="101.83327,66.442993,57.194206" Radius="26.300684" texID="13" />
 <Sprite Angle="-1.5114954" Pos="-77.661339,12.40692,49.197411" Radius="22.460478" texID="14" />
 <Sprite Angle="1.2953894" Pos="-174.20665,-87.92878,56.414368" Radius="22.330378" texID="14" />
 <Sprite Angle="-0.81984121" Pos="-31.97513,-36.099197,51.81657" Radius="22.052874" texID="15" />
 <Sprite Angle="-3.0428371" Pos="4.5555263,-16.872538,54.30212" Radius="26.422667" texID="14" />
 <Sprite Angle="2.5346909" Pos="-86.890137,115.64494,52.176445" Radius="25.78776" texID="15" />
 <Sprite Angle="0.0045061996" Pos="7.1648588,13.679543,48.072132" Radius="23.133839" texID="15" />
 <Sprite Angle="-0.59664041" Pos="-1.358961,122.83205,52.08379" Radius="25.767677" texID="14" />
 <Sprite Angle="0.66298699" Pos="-49.645348,84.662544,52.900223" Radius="21.689276" texID="14" />
 <Sprite Angle="2.6785059" Pos="-83.438492,-115.9173,48.997665" Radius="22.117176" texID="15" />
 <Sprite Angle="1.8501316" Pos="-157.00336,-147.10112,58.856945" Radius="24.577547" texID="13" />
 <Sprite Angle="-3.0263464" Pos="-178.71118,69.253746,48.102345" Radius="27.375881" texID="14" />
 <Sprite Angle="1.0152378" Pos="6.2035255,-46.655552,56.783978" Radius="27.002029" texID="13" />
 <Sprite Angle="3.0368929" Pos="43.439159,-59.390926,53.088886" Radius="25.953321" texID="12" />
 <Sprite Angle="-0.56787741" Pos="59.61702,-97.267448,53.021412" Radius="22.473297" texID="12" />
 <Sprite Angle="-1.7042074" Pos="-128.66692,70.920059,57.302303" Radius="26.677313" texID="13" />
 <Sprite Angle="1.8322986" Pos="-85.498489,-117.30895,53.389343" Radius="28.318842" texID="14" />
 <Sprite Angle="-2.7007494" Pos="-184.06717,11.170921,51.409698" Radius="27.963148" texID="14" />
 <Sprite Angle="-2.4537711" Pos="64.423683,130.44031,57.330837" Radius="22.395535" texID="14" />
 <Sprite Angle="2.0344067" Pos="-75.280891,11.344876,58.24865" Radius="26.637791" texID="13" />
 <Sprite Angle="-0.86260217" Pos="-186.21873,-84.687714,53.626011" Radius="21.784342" texID="14" />
 <Sprite Angle="0.21792762" Pos="60.312843,147.13087,57.0042" Radius="22.950758" texID="15" />
 <Sprite Angle="-2.2533889" Pos="35.36396,29.097494,58.578312" Radius="26.748024" texID="13" />
 <Sprite Angle="-1.9903033" Pos="109.26759,-44.110306,49.381378" Radius="26.799723" texID="15" />
 <Sprite Angle="-0.89922708" Pos="96.907585,-31.658754,56.083027" Radius="25.733925" texID="13" />
 <Sprite Angle="1.342369" Pos="36.911251,34.957047,52.923721" Radius="24.705297" texID="13" />
 <Sprite Angle="-0.59970844" Pos="47.88876,36.833935,56.481842" Radius="22.704229" texID="13" />
 <Sprite Angle="1.4369034" Pos="-146.49278,5.2472787,54.128899" Radius="24.565798" texID="14" />
 <Sprite Angle="2.2079432" Pos="106.74981,146.28857,56.612095" Radius="23.571566" texID="12" />
 <Sprite Angle="-1.9206969" Pos="7.7965918,-6.4443626,58.531651" Radius="25.721748" texID="12" />
 <Sprite Angle="-1.6135081" Pos="-160.61064,143.40457,51.953537" Radius="27.024887" texID="13" />
 <Sprite Angle="3.1260581" Pos="-126.94568,36.458557,50.394196" Radius="24.361141" texID="12" />
 <Sprite Angle="-2.3600037" Pos="-130.53465,41.430023,48.283627" Radius="26.524567" texID="14" />
 <Sprite Angle="1.2660512" Pos="-58.187477,59.017841,54.175224" Radius="27.80015" texID="14" />
 <Sprite Angle="2.2903972" Pos="111.19025,-115.66095,58.743141" Radius="26.748878" texID="13" />
 <Sprite Angle="-0.99203569" Pos="-5.6254487,-68.555634,55.420349" Radius="26.666204" texID="13" />
 <Sprite Angle="-0.72089654" Pos="65.137817,21.736429,55.719795" Radius="25.272484" texID="14" />
 <Sprite Angle="0.68369639" Pos="57.145023,-143.16423,50.239769" Radius="24.517517" texID="14" />
 <Sprite Angle="-0.74467391" Pos="-32.084995,22.642828,50.457977" Radius="25.75956" texID="14" />
 <Sprite Angle="-1.5444769" Pos="16.128145,-6.98454,58.027424" Radius="24.928968" texID="15" />
 <Sprite Angle="-2.3239541" Pos="-64.010406,6.245234,49.799664" Radius="26.450651" texID="14" />
 <Sprite Angle="-2.6652749" Pos="-98.60009,-138.2477,58.572269" Radius="26.576265" texID="14" />
 <Sprite Angle="-0.11955819" Pos="94.572922,-82.160782,51.958908" Radius="22.226341" texID="14" />
 <Sprite Angle="-1.1686405" Pos="8.0346365,48.379089,51.226738" Radius="24.349178" texID="12" />
 <Sprite Angle="-2.3728511" Pos="32.086273,-72.080521,50.743996" Radius="27.02916" texID="13" />
 <Sprite Angle="1.944666" Pos="-130.79102,144.96101,54.281979" Radius="25.025742" texID="13" />
 <Sprite Angle="1.3613526" Pos="-29.146063,-117.30895,56.127342" Radius="21.921278" texID="13" />
 <Sprite Angle="1.6618299" Pos="47.156315,-59.848701,55.208519" Radius="26.538027" texID="12" />
 <Sprite Angle="3.1291261" Pos="-105.43929,84.085747,56.570133" Radius="24.566866" texID="14" />
 <Sprite Angle="-0.30785993" Pos="57.309822,-91.124069,48.918442" Radius="25.360714" texID="12" />
 <Sprite Angle="-0.45838624" Pos="-76.754936,127.31827,52.011616" Radius="24.410063" texID="12" />
 <Sprite Angle="1.3222349" Pos="-8.2530918,-95.106735,53.705574" Radius="22.054369" texID="14" />
 <Sprite Angle="-0.024065042" Pos="-23.689354,-125.71375,49.92421" Radius="28.340418" texID="14" />
 <Sprite Angle="0.5496608" Pos="57.053467,-90.547272,55.019855" Radius="26.494019" texID="12" />
 <Sprite Angle="-1.3924166" Pos="-85.663292,-109.19713,54.346096" Radius="24.118244" texID="13" />
 <Sprite Angle="2.7832031" Pos="-107.41689,-60.883278,52.731026" Radius="25.814249" texID="12" />
 <Sprite Angle="-1.1642301" Pos="0.16086084,25.728251,50.289791" Radius="22.347469" texID="14" />
 <Sprite Angle="-0.69980365" Pos="-15.42189,-34.103287,52.039814" Radius="21.603397" texID="12" />
 <Sprite Angle="-0.42329541" Pos="-130.11349,60.391174,57.445313" Radius="26.273552" texID="13" />
 <Sprite Angle="-0.7013377" Pos="-158.2119,-47.214039,52.69175" Radius="22.375881" texID="14" />
 <Sprite Angle="0.5686444" Pos="54.608932,-93.916512,57.567844" Radius="27.187674" texID="14" />
 <Sprite Angle="2.3160923" Pos="48.328224,-42.068619,52.648781" Radius="27.855694" texID="14" />
 <Sprite Angle="-1.0023904" Pos="43.201115,-21.926403,56.473785" Radius="21.721535" texID="12" />
 <Sprite Angle="-1.9933714" Pos="-140.83466,110.36218,54.877518" Radius="24.100727" texID="15" />
 <Sprite Angle="-3.1105261" Pos="-72.964539,123.96733,52.034779" Radius="22.812754" texID="15" />
 <Sprite Angle="1.7128363" Pos="-145.8519,110.60938,49.408234" Radius="26.00267" texID="15" />
 <Sprite Angle="-2.1414049" Pos="-82.87085,134.78004,48.090595" Radius="25.617496" texID="12" />
 <Sprite Angle="-0.8112123" Pos="-184.02139,-140.73801,58.323177" Radius="25.18746" texID="14" />
 <Sprite Angle="0.091370441" Pos="-25.630331,-83.250298,50.674843" Radius="26.159689" texID="13" />
 <Sprite Angle="-2.5851221" Pos="-152.1326,-33.471554,50.823559" Radius="26.854839" texID="13" />
 <Sprite Angle="1.8583771" Pos="-156.50896,-48.028885,54.469635" Radius="25.991989" texID="15" />
 <Sprite Angle="-1.6927022" Pos="-3.611227,145.98643,58.046894" Radius="26.58246" texID="15" />
 <Sprite Angle="1.2959646" Pos="-68.670586,126.04564,54.886917" Radius="22.651676" texID="12" />
 <Sprite Angle="-1.9853177" Pos="95.360298,-54.364525,52.76762" Radius="26.629032" texID="13" />
 <Sprite Angle="0.46989146" Pos="20.065033,-49.164173,49.691566" Radius="24.193228" texID="12" />
 <Sprite Angle="-1.7465849" Pos="-103.85538,119.48111,55.664406" Radius="26.765968" texID="13" />
 <Sprite Angle="1.7465849" Pos="-143.92923,60.501041,54.564976" Radius="24.578188" texID="12" />
 <Sprite Angle="0.42559645" Pos="0.14254974,92.463074,55.283382" Radius="26.170797" texID="14" />
 <Sprite Angle="0.19721825" Pos="104.98279,-91.14238,52.517185" Radius="27.203268" texID="15" />
 <Sprite Angle="0.38762927" Pos="59.031067,22.285763,49.376675" Radius="27.411131" texID="13" />
 <Sprite Angle="-2.2367063" Pos="-86.514755,-53.760258,55.558323" Radius="25.348751" texID="13" />
 <Sprite Angle="-1.405264" Pos="-141.56709,-89.100693,58.757915" Radius="23.052019" texID="14" />
</Cloud>
