<Graph Description="" Group="" enabled="1" MultiPlayer="ServerOnly">
 <Nodes>
  <Node Id="1" Class="AI:ActionStart" pos="-100,10,0" flags="0"/>
  <Node Id="2" Class="AI:ActionEnd" pos="360,10,0" flags="0">
   <Inputs />
  </Node>
  <Node Id="1065" Class="AI:AIFollowPathSpeedStance" pos="50,10,0" flags="0">
   <Inputs entityId="0" PathFindToStart="0" Reverse="0" StartNearest="0" Loops="0" path_name="Marines_LTV_2_path" run="2" stance="4"/>
  </Node>
 </Nodes>
 <Edges>
  <Edge nodeIn="1065" nodeOut="1" portIn="entityId" portOut="UserId" enabled="1"/>
  <Edge nodeIn="2" nodeOut="1065" portIn="cancel" portOut="fail" enabled="1"/>
  <Edge nodeIn="2" nodeOut="1065" portIn="end" portOut="succeed" enabled="1"/>
 </Edges>
</Graph>
